pyPreservicaFSDate/__init__.py
pyPreservicaFSDate/__main__.py
pypreservicafsdate-0.1.0.dist-info/licenses/LICENSE
pypreservicafsdate-0.1.0.dist-info/METADATA
pypreservicafsdate-0.1.0.dist-info/WHEEL
pypreservicafsdate-0.1.0.dist-info/top_level.txt
pypreservicafsdate-0.1.0.dist-info/RECORD
