Metadata-Version: 2.4
Name: pyPreservicaFSDate
Version: 0.1.0
Summary: Python module to add local file system dates to existing Preservica assets
Home-page: https://github.com/carj/pyPreservicaFSDate
Author: James Carr
Author-email: drjamescarr@gmail.com
License: Apache License 2.0
Project-URL: Documentation, https://github.com/carj/preserva-tweet
Project-URL: Source, https://github.com/carj/pyPreservicaFSDate
Keywords: Preservica API Preservation
Classifier: Programming Language :: Python :: 3
Classifier: Programming Language :: Python :: 3.8
Classifier: Programming Language :: Python :: 3.9
Classifier: Programming Language :: Python :: 3.10
Classifier: Programming Language :: Python :: 3.11
Classifier: Programming Language :: Python :: 3.12
Classifier: Programming Language :: Python :: 3.13
Classifier: Operating System :: OS Independent
Classifier: Topic :: System :: Archiving
License-File: LICENSE
Requires-Dist: pyPreservica
Dynamic: author
Dynamic: author-email
Dynamic: classifier
Dynamic: description
Dynamic: description-content-type
Dynamic: home-page
Dynamic: keywords
Dynamic: license
Dynamic: license-file
Dynamic: project-url
Dynamic: requires-dist
Dynamic: summary
